CHANGES.txt
bootstrap.py
setup.py
gocept/__init__.py
gocept.imapapi.egg-info/PKG-INFO
gocept.imapapi.egg-info/SOURCES.txt
gocept.imapapi.egg-info/dependency_links.txt
gocept.imapapi.egg-info/namespace_packages.txt
gocept.imapapi.egg-info/not-zip-safe
gocept.imapapi.egg-info/requires.txt
gocept.imapapi.egg-info/top_level.txt
gocept/imapapi/README.txt
gocept/imapapi/__init__.py
gocept/imapapi/account.py
gocept/imapapi/account.txt
gocept/imapapi/folder.py
gocept/imapapi/folder.txt
gocept/imapapi/imap.py
gocept/imapapi/imap.txt
gocept/imapapi/interfaces.py
gocept/imapapi/message.py
gocept/imapapi/message.txt
gocept/imapapi/optimizations.txt
gocept/imapapi/parser.py
gocept/imapapi/testing.py
gocept/imapapi/testmessages/00-header-encoding
gocept/imapapi/testmessages/01-multipart-alternative
gocept/imapapi/testmessages/02-multipart-mixed
gocept/imapapi/testmessages/03-mixed-with-cid
gocept/imapapi/testmessages/04-encoded-attachment-filename
gocept/imapapi/testmessages/05-claws-nested-messages
gocept/imapapi/testmessages/06-umlaut-subject
gocept/imapapi/testmessages/07-injection
gocept/imapapi/tests/__init__.py
gocept/imapapi/tests/test_doctest.py
profiles/dev.cfg
profiles/dovecot-passwd.in
profiles/dovecot.conf.in