Metadata-Version: 1.0
Name: gocept.imapapi
Version: 0.4
Summary: Object-oriented API for accessing IMAP accounts.
Home-page: UNKNOWN
Author: gocept gmbh & co. kg
Author-email: mail@gocept.com
License: ZPL 2.1
Platform: UNKNOWN
Classifier: Development Status :: 2 - Pre-Alpha
Classifier: Intended Audience :: Developers
Classifier: Intended Audience :: System Administrators
Classifier: License :: OSI Approved :: Zope Public License
Classifier: Natural Language :: English
Classifier: Operating System :: OS Independent
Classifier: Programming Language :: Python
Classifier: Topic :: Communications :: Email :: Post-Office :: IMAP
Classifier: Topic :: Software Development :: Libraries :: Python Modules
